<openerp>
	<data>
	
		<record id="sequence_inherit_form_omnia" model="ir.ui.view">
            <field name="name">ir.sequence.form.omnia</field>
            <field name="model">ir.sequence</field>
            <field name="inherit_id" ref="base.sequence_view"/>
            <field name="arch" type="xml">
                <xpath expr="//field[@name='active']" position="after">
                    <field name="use_for_ddt"/>
                </xpath>
            </field>
        </record>

    </data>
</openerp>
	
